LICENSE
p123dav/__init__.py
p123dav/__main__.py
p123dav/dav.py
p123dav/py.typed
p123dav-0.0.3.1.dist-info/LICENSE
p123dav-0.0.3.1.dist-info/LICENSE_zh
p123dav-0.0.3.1.dist-info/METADATA
p123dav-0.0.3.1.dist-info/WHEEL
p123dav-0.0.3.1.dist-info/entry_points.txt
p123dav-0.0.3.1.dist-info/RECORD
