Metadata-Version: 2.1
Name: p123dav
Version: 0.0.3.1
Summary: 123 WebDAV
Home-page: https://github.com/ChenyangGao/p123client/tree/main/modules/p123dav
License: MIT
Keywords: python-123,webdav
Author: ChenyangGao
Author-email: wosiwujm@gmail.com
Requires-Python: >=3.12,<4.0
Classifier: Development Status :: 5 - Production/Stable
Classifier: Intended Audience :: Developers
Classifier: License :: OSI Approved :: MIT License
Classifier: Operating System :: OS Independent
Classifier: Programming Language :: Python
Classifier: Programming Language :: Python :: 3
Classifier: Programming Language :: Python :: 3.12
Classifier: Programming Language :: Python :: 3.13
Classifier: Programming Language :: Python :: 3 :: Only
Classifier: Topic :: Software Development
Classifier: Topic :: Software Development :: Libraries
Classifier: Topic :: Software Development :: Libraries :: Python Modules
Requires-Dist: WsgiDAV
Requires-Dist: cachedict (>=0.0.3)
Requires-Dist: cheroot
Requires-Dist: p123client (>=0.0.8.5)
Requires-Dist: python-property (>=0.0.3)
Project-URL: Repository, https://github.com/ChenyangGao/p123client/tree/main/modules/p123dav
